passless_models/__init__.py
passless_models/discount.py
passless_models/fee.py
passless_models/item.py
passless_models/jsonable.py
passless_models/loyalty.py
passless_models/payment.py
passless_models/price.py
passless_models/receipt.py
passless_models/tax_class.py
passless_models/vendor.py
passless_models-0.0.3.dist-info/LICENSE
passless_models-0.0.3.dist-info/METADATA
passless_models-0.0.3.dist-info/WHEEL
passless_models-0.0.3.dist-info/top_level.txt
passless_models-0.0.3.dist-info/RECORD
